gi_data/__init__.py
gi_data/dataclient.py
gi_data/drivers/__init__.py
gi_data/drivers/base.py
gi_data/drivers/cloud_gql.py
gi_data/drivers/kafka_stream.py
gi_data/drivers/local_http.py
gi_data/drivers/ws_stream.py
gi_data/infra/__init__.py
gi_data/infra/auth.py
gi_data/infra/http.py
gi_data/infra/ws.py
gi_data/mapping/__init__.py
gi_data/mapping/enums.py
gi_data/mapping/models.py
gi_data/utils/__init__.py
gi_data/utils/logging.py
gi_data/ws/__init__.py
gi_data/ws/enums.py
pygidata-0.4.2.dist-info/licenses/LICENSE
pygidata-0.4.2.dist-info/METADATA
pygidata-0.4.2.dist-info/WHEEL
pygidata-0.4.2.dist-info/top_level.txt
pygidata-0.4.2.dist-info/RECORD
