Metadata-Version: 2.4
Name: pygidata
Version: 0.4.2
Summary: Python package providing an interface to the Gantner Instruments Data API
Author: Gantner Instruments GmbH
Keywords: python
Classifier: Development Status :: 1 - Planning
Classifier: Intended Audience :: Developers
Classifier: Programming Language :: Python :: 3.10
Classifier: Programming Language :: Python :: 3.11
Classifier: Programming Language :: Python :: 3.12
Classifier: Operating System :: Unix
Classifier: Operating System :: MacOS :: MacOS X
Classifier: Operating System :: Microsoft :: Windows
Requires-Python: <3.13,>=3.10
License-File: LICENSE
Requires-Dist: aiokafka
Requires-Dist: certifi
Requires-Dist: httpx
Requires-Dist: nest_asyncio
Requires-Dist: pandas
Requires-Dist: pydantic
Requires-Dist: websockets
Provides-Extra: test
Requires-Dist: pytest; extra == "test"
Requires-Dist: pytest-xdist; extra == "test"
Dynamic: license-file
